{
  "main": {
    "id": "3b259073ed097626",
    "type": "split",
    "children": [
      {
        "id": "8ecef0eabe744229",
        "type": "tabs",
        "children": [
          {
            "id": "a38eb43ff6632818",
            "type": "leaf",
            "pane-relief:history-v1": {
              "pos": 0,
              "stack": [
                {
                  "state": "{}",
                  "eState": "{}"
                },
                {
                  "title": "Github Actions + Docker Automation",
                  "icon": "lucide-file",
                  "state": "{\"type\":\"markdown\",\"state\":{\"file\":\"Intrend Engineering/Github Actions + Docker Automation.md\",\"mode\":\"source\",\"backlinks\":false,\"source\":false}}",
                  "eState": "{\"cursor\":{\"from\":{\"line\":5,\"ch\":0},\"to\":{\"line\":9,\"ch\":0}}}"
                },
                {
                  "title": "Design",
                  "icon": "lucide-file",
                  "state": "{\"type\":\"markdown\",\"state\":{\"file\":\"Intrend Engineering/Design.md\",\"mode\":\"source\",\"backlinks\":false,\"source\":false}}",
                  "eState": "{\"cursor\":{\"from\":{\"line\":6,\"ch\":3},\"to\":{\"line\":6,\"ch\":3}},\"scroll\":0}"
                },
                {
                  "title": "Talos",
                  "icon": "lucide-file",
                  "state": "{\"type\":\"markdown\",\"state\":{\"file\":\"Intrend Engineering/Talos.md\",\"mode\":\"source\",\"backlinks\":false,\"source\":false}}",
                  "eState": "{\"cursor\":{\"from\":{\"line\":0,\"ch\":0},\"to\":{\"line\":0,\"ch\":0}},\"scroll\":108.92469387882133}"
                },
                {
                  "title": "ArgoCD + Kustomize Helm",
                  "icon": "lucide-file",
                  "state": "{\"type\":\"markdown\",\"state\":{\"file\":\"Intrend Engineering/ArgoCD + Kustomize Helm.md\",\"mode\":\"source\",\"backlinks\":false,\"source\":false}}",
                  "eState": "{\"cursor\":{\"from\":{\"line\":36,\"ch\":13},\"to\":{\"line\":36,\"ch\":13}},\"scroll\":27.27927854352921}"
                },
                {
                  "title": "Terraform",
                  "icon": "lucide-file",
                  "state": "{\"type\":\"markdown\",\"state\":{\"file\":\"Intrend Engineering/Terraform.md\",\"mode\":\"source\",\"backlinks\":false,\"source\":false}}",
                  "eState": "{\"cursor\":{\"from\":{\"line\":23,\"ch\":26},\"to\":{\"line\":23,\"ch\":26}},\"scroll\":5.776974007851465}"
                },
                {
                  "title": "Why Kafka",
                  "icon": "lucide-file",
                  "state": "{\"type\":\"markdown\",\"state\":{\"file\":\"Intrend Engineering/Why Kafka.md\",\"mode\":\"source\",\"backlinks\":false,\"source\":false}}",
                  "eState": "{\"cursor\":{\"from\":{\"line\":0,\"ch\":0},\"to\":{\"line\":0,\"ch\":0}}}"
                },
                {
                  "title": "Intrend LOG",
                  "icon": "lucide-file",
                  "state": "{\"type\":\"markdown\",\"state\":{\"file\":\"Intrend Engineering/Intrend LOG.md\",\"mode\":\"source\",\"backlinks\":false,\"source\":false}}",
                  "eState": "{\"cursor\":{\"from\":{\"line\":22,\"ch\":26},\"to\":{\"line\":22,\"ch\":26}}}"
                },
                {
                  "title": "Handling DB Transactions",
                  "icon": "lucide-file",
                  "state": "{\"type\":\"markdown\",\"state\":{\"file\":\"Intrend Engineering/Handling DB Transactions.md\",\"mode\":\"source\",\"backlinks\":false,\"source\":false}}",
                  "eState": "{\"cursor\":{\"from\":{\"line\":0,\"ch\":0},\"to\":{\"line\":0,\"ch\":0}}}"
                },
                {
                  "title": "Error Tracking with Sentry",
                  "icon": "lucide-file",
                  "state": "{\"type\":\"markdown\",\"state\":{\"file\":\"Intrend Engineering/Error Tracking with Sentry.md\",\"mode\":\"source\",\"backlinks\":false,\"source\":false}}",
                  "eState": "{\"cursor\":{\"from\":{\"line\":0,\"ch\":0},\"to\":{\"line\":0,\"ch\":0}}}"
                },
                {
                  "title": "Design",
                  "icon": "lucide-file",
                  "state": "{\"type\":\"markdown\",\"state\":{\"file\":\"Intrend Engineering/Design.md\",\"mode\":\"source\",\"backlinks\":false,\"source\":false}}",
                  "eState": "{\"cursor\":{\"from\":{\"line\":0,\"ch\":0},\"to\":{\"line\":0,\"ch\":0}}}"
                },
                {
                  "title": "Emails",
                  "icon": "lucide-file",
                  "state": "{\"type\":\"markdown\",\"state\":{\"file\":\"Intrend Engineering/Emails.md\",\"mode\":\"source\",\"backlinks\":false,\"source\":false}}",
                  "eState": "{\"cursor\":{\"from\":{\"line\":0,\"ch\":0},\"to\":{\"line\":0,\"ch\":0}}}"
                },
                {
                  "title": "Proxmox",
                  "icon": "lucide-file",
                  "state": "{\"type\":\"markdown\",\"state\":{\"file\":\"Intrend Engineering/Proxmox.md\",\"mode\":\"source\",\"backlinks\":false,\"source\":false}}",
                  "eState": "{\"cursor\":{\"from\":{\"line\":0,\"ch\":0},\"to\":{\"line\":0,\"ch\":0}}}"
                },
                {
                  "title": "Redpanda",
                  "icon": "lucide-file",
                  "state": "{\"type\":\"markdown\",\"state\":{\"file\":\"Intrend Engineering/Redpanda.md\",\"mode\":\"source\",\"backlinks\":false,\"source\":false}}",
                  "eState": "{\"cursor\":{\"from\":{\"line\":0,\"ch\":0},\"to\":{\"line\":0,\"ch\":0}}}"
                },
                {
                  "title": "STAR Problems",
                  "icon": "lucide-file",
                  "state": "{\"type\":\"markdown\",\"state\":{\"file\":\"Intrend Engineering/STAR Problems.md\",\"mode\":\"source\",\"backlinks\":false,\"source\":false}}",
                  "eState": "{\"cursor\":{\"from\":{\"line\":0,\"ch\":0},\"to\":{\"line\":0,\"ch\":0}}}"
                },
                {
                  "title": "Talos",
                  "icon": "lucide-file",
                  "state": "{\"type\":\"markdown\",\"state\":{\"file\":\"Intrend Engineering/Talos.md\",\"mode\":\"source\",\"backlinks\":false,\"source\":false}}",
                  "eState": "{\"cursor\":{\"from\":{\"line\":0,\"ch\":0},\"to\":{\"line\":0,\"ch\":0}}}"
                },
                {
                  "title": "Colors",
                  "icon": "lucide-file",
                  "state": "{\"type\":\"markdown\",\"state\":{\"file\":\"Intrend Research/Colors.md\",\"mode\":\"source\",\"backlinks\":false,\"source\":false}}",
                  "eState": "{\"cursor\":{\"from\":{\"line\":0,\"ch\":0},\"to\":{\"line\":0,\"ch\":0}}}"
                },
                {
                  "title": "Why Kafka",
                  "icon": "lucide-file",
                  "state": "{\"type\":\"markdown\",\"state\":{\"file\":\"Intrend Engineering/Why Kafka.md\",\"mode\":\"source\",\"backlinks\":false,\"source\":false}}",
                  "eState": "{\"cursor\":{\"from\":{\"line\":0,\"ch\":0},\"to\":{\"line\":0,\"ch\":0}}}"
                },
                {
                  "title": "STAR Problems",
                  "icon": "lucide-file",
                  "state": "{\"type\":\"markdown\",\"state\":{\"file\":\"Intrend Engineering/STAR Problems.md\",\"mode\":\"source\",\"backlinks\":false,\"source\":false}}",
                  "eState": "{\"cursor\":{\"from\":{\"line\":0,\"ch\":0},\"to\":{\"line\":0,\"ch\":0}}}"
                },
                {
                  "title": "Redpanda",
                  "icon": "lucide-file",
                  "state": "{\"type\":\"markdown\",\"state\":{\"file\":\"Intrend Engineering/Redpanda.md\",\"mode\":\"source\",\"backlinks\":false,\"source\":false}}",
                  "eState": "{\"cursor\":{\"from\":{\"line\":0,\"ch\":0},\"to\":{\"line\":0,\"ch\":0}}}"
                },
                {
                  "title": "Production Setup",
                  "icon": "lucide-file",
                  "state": "{\"type\":\"markdown\",\"state\":{\"file\":\"Intrend Engineering/Production Setup.md\",\"mode\":\"source\",\"backlinks\":false,\"source\":false}}",
                  "eState": "{\"cursor\":{\"from\":{\"line\":0,\"ch\":0},\"to\":{\"line\":0,\"ch\":0}}}"
                },
                {
                  "title": "Intrend LOG",
                  "icon": "lucide-file",
                  "state": "{\"type\":\"markdown\",\"state\":{\"file\":\"Intrend Engineering/Intrend LOG.md\",\"mode\":\"source\",\"backlinks\":false,\"source\":false}}",
                  "eState": "{\"cursor\":{\"from\":{\"line\":0,\"ch\":0},\"to\":{\"line\":0,\"ch\":0}}}"
                },
                {
                  "title": "Emails",
                  "icon": "lucide-file",
                  "state": "{\"type\":\"markdown\",\"state\":{\"file\":\"Intrend Engineering/Emails.md\",\"mode\":\"source\",\"backlinks\":false,\"source\":false}}",
                  "eState": "{\"cursor\":{\"from\":{\"line\":0,\"ch\":0},\"to\":{\"line\":0,\"ch\":0}}}"
                },
                {
                  "title": "Persistent Volumes",
                  "icon": "lucide-file",
                  "state": "{\"type\":\"markdown\",\"state\":{\"file\":\"Intrend Engineering/Persistent Volumes.md\",\"mode\":\"source\",\"backlinks\":false,\"source\":false}}",
                  "eState": "{\"cursor\":{\"from\":{\"line\":0,\"ch\":0},\"to\":{\"line\":0,\"ch\":0}}}"
                },
                {
                  "title": "Redpanda",
                  "icon": "lucide-file",
                  "state": "{\"type\":\"markdown\",\"state\":{\"file\":\"Intrend Engineering/Redpanda.md\",\"mode\":\"source\",\"backlinks\":false,\"source\":false}}",
                  "eState": "{\"cursor\":{\"from\":{\"line\":84,\"ch\":57},\"to\":{\"line\":84,\"ch\":57}},\"scroll\":30.01169610862517}"
                }
              ]
            },
            "state": {
              "type": "markdown",
              "state": {
                "file": "Intrend Engineering/Kubernetes.md",
                "mode": "source",
                "backlinks": false,
                "source": false
              },
              "icon": "lucide-file",
              "title": "Kubernetes"
            }
          },
          {
            "id": "1e41539860bc5a7d",
            "type": "leaf",
            "pane-relief:history-v1": {
              "pos": 0,
              "stack": [
                {
                  "state": "{}",
                  "eState": "{}"
                }
              ]
            },
            "state": {
              "type": "release-notes",
              "state": {
                "currentVersion": "1.7.4"
              },
              "icon": "lucide-file",
              "title": "Release Notes 1.7.4"
            }
          },
          {
            "id": "859e6b650c9cf42d",
            "type": "leaf",
            "pane-relief:history-v1": {
              "pos": 0,
              "stack": [
                {
                  "state": "{}",
                  "eState": "{}"
                },
                {
                  "title": "ArgoCD + Kustomize Helm",
                  "icon": "lucide-file",
                  "state": "{\"type\":\"markdown\",\"state\":{\"file\":\"Intrend Engineering/ArgoCD + Kustomize Helm.md\",\"mode\":\"source\",\"backlinks\":false,\"source\":false}}",
                  "eState": "{\"cursor\":{\"from\":{\"line\":0,\"ch\":0},\"to\":{\"line\":0,\"ch\":0}}}"
                },
                {
                  "title": "Kubernetes",
                  "icon": "lucide-file",
                  "state": "{\"type\":\"markdown\",\"state\":{\"file\":\"Intrend Engineering/Kubernetes.md\",\"mode\":\"source\",\"backlinks\":false,\"source\":false}}",
                  "eState": "{\"cursor\":{\"from\":{\"line\":122,\"ch\":0},\"to\":{\"line\":121,\"ch\":101}},\"scroll\":37.872268219253236}"
                },
                {
                  "title": "Talos",
                  "icon": "lucide-file",
                  "state": "{\"type\":\"markdown\",\"state\":{\"file\":\"Intrend Engineering/Talos.md\",\"mode\":\"source\",\"backlinks\":false,\"source\":false}}",
                  "eState": "{\"cursor\":{\"from\":{\"line\":163,\"ch\":0},\"to\":{\"line\":163,\"ch\":0}},\"scroll\":147.47836207912098}"
                },
                {
                  "title": "Terraform",
                  "icon": "lucide-file",
                  "state": "{\"type\":\"markdown\",\"state\":{\"file\":\"Intrend Engineering/Terraform.md\",\"mode\":\"source\",\"backlinks\":false,\"source\":false}}",
                  "eState": "{\"cursor\":{\"from\":{\"line\":32,\"ch\":53},\"to\":{\"line\":32,\"ch\":53}},\"scroll\":1.8802822478354673}"
                },
                {
                  "title": "Proxmox",
                  "icon": "lucide-file",
                  "state": "{\"type\":\"markdown\",\"state\":{\"file\":\"Intrend Engineering/Proxmox.md\",\"mode\":\"source\",\"backlinks\":false,\"source\":false}}",
                  "eState": "{\"cursor\":{\"from\":{\"line\":89,\"ch\":0},\"to\":{\"line\":89,\"ch\":0}},\"scroll\":86.08330438982168}"
                }
              ]
            },
            "state": {
              "type": "markdown",
              "state": {
                "file": "Intrend Engineering/Postgres.md",
                "mode": "source",
                "backlinks": false,
                "source": false
              },
              "icon": "lucide-file",
              "title": "Postgres"
            }
          },
          {
            "id": "9d4d57adf2bf1d34",
            "type": "leaf",
            "pane-relief:history-v1": {
              "pos": 0,
              "stack": [
                {
                  "state": "{}",
                  "eState": "{}"
                },
                {
                  "title": "Proxmox",
                  "icon": "lucide-file",
                  "state": "{\"type\":\"markdown\",\"state\":{\"file\":\"Intrend Engineering/Proxmox.md\",\"mode\":\"source\",\"backlinks\":false,\"source\":false}}",
                  "eState": "{\"cursor\":{\"from\":{\"line\":0,\"ch\":0},\"to\":{\"line\":0,\"ch\":0}}}"
                },
                {
                  "title": "Untitled",
                  "icon": "lucide-file",
                  "state": "{\"type\":\"markdown\",\"state\":{\"file\":\"Intrend Engineering/Untitled.md\",\"mode\":\"source\",\"backlinks\":false,\"source\":false}}",
                  "eState": "{\"cursor\":{\"from\":{\"line\":0,\"ch\":0},\"to\":{\"line\":0,\"ch\":0}}}"
                },
                {
                  "title": "Github Actions + Docker Automation",
                  "icon": "lucide-file",
                  "state": "{\"type\":\"markdown\",\"state\":{\"file\":\"Intrend Engineering/Github Actions + Docker Automation.md\",\"mode\":\"source\",\"backlinks\":false,\"source\":false}}",
                  "eState": "{\"cursor\":{\"from\":{\"line\":2,\"ch\":4},\"to\":{\"line\":2,\"ch\":4}}}"
                },
                {
                  "title": "SSL",
                  "icon": "lucide-file",
                  "state": "{\"type\":\"markdown\",\"state\":{\"file\":\"Intrend Engineering/SSL.md\",\"mode\":\"source\",\"backlinks\":false,\"source\":false}}",
                  "eState": "{\"cursor\":{\"from\":{\"line\":21,\"ch\":86},\"to\":{\"line\":21,\"ch\":86}},\"scroll\":0}"
                },
                {
                  "title": "ArgoCD + Kustomize Helm",
                  "icon": "lucide-file",
                  "state": "{\"type\":\"markdown\",\"state\":{\"file\":\"Intrend Engineering/ArgoCD + Kustomize Helm.md\",\"mode\":\"source\",\"backlinks\":false,\"source\":false}}",
                  "eState": "{\"cursor\":{\"from\":{\"line\":16,\"ch\":0},\"to\":{\"line\":16,\"ch\":0}},\"scroll\":38.0338244354933}"
                },
                {
                  "title": "Apache Pulsar",
                  "icon": "lucide-file",
                  "state": "{\"type\":\"markdown\",\"state\":{\"file\":\"Intrend Engineering/Apache Pulsar.md\",\"mode\":\"source\",\"backlinks\":false,\"source\":false}}",
                  "eState": "{\"cursor\":{\"from\":{\"line\":0,\"ch\":0},\"to\":{\"line\":0,\"ch\":0}}}"
                },
                {
                  "title": "Talos",
                  "icon": "lucide-file",
                  "state": "{\"type\":\"markdown\",\"state\":{\"file\":\"Intrend Engineering/Talos.md\",\"mode\":\"source\",\"backlinks\":false,\"source\":false}}",
                  "eState": "{\"cursor\":{\"from\":{\"line\":0,\"ch\":0},\"to\":{\"line\":0,\"ch\":0}}}"
                },
                {
                  "title": "Proxmox",
                  "icon": "lucide-file",
                  "state": "{\"type\":\"markdown\",\"state\":{\"file\":\"Intrend Engineering/Proxmox.md\",\"mode\":\"source\",\"backlinks\":false,\"source\":false}}",
                  "eState": "{\"cursor\":{\"from\":{\"line\":0,\"ch\":0},\"to\":{\"line\":0,\"ch\":0}},\"scroll\":0}"
                },
                {
                  "title": "ArgoCD + Kustomize Helm",
                  "icon": "lucide-file",
                  "state": "{\"type\":\"markdown\",\"state\":{\"file\":\"Intrend Engineering/ArgoCD + Kustomize Helm.md\",\"mode\":\"source\",\"backlinks\":false,\"source\":false}}",
                  "eState": "{\"cursor\":{\"from\":{\"line\":38,\"ch\":48},\"to\":{\"line\":38,\"ch\":48}},\"scroll\":11.811470773749221}"
                }
              ]
            },
            "state": {
              "type": "markdown",
              "state": {
                "file": "Intrend Engineering/Proxies.md",
                "mode": "source",
                "backlinks": false,
                "source": false
              },
              "icon": "lucide-file",
              "title": "Proxies"
            }
          }
        ],
        "currentTab": 1
      }
    ],
    "direction": "vertical"
  },
  "left": {
    "id": "0612b6e93da102f9",
    "type": "split",
    "children": [
      {
        "id": "cbe25c5d94f37c08",
        "type": "tabs",
        "children": [
          {
            "id": "602e749129210847",
            "type": "leaf",
            "pane-relief:history-v1": {
              "pos": 0,
              "stack": [
                {
                  "state": "{}",
                  "eState": "{}"
                }
              ]
            },
            "state": {
              "type": "file-explorer",
              "state": {
                "sortOrder": "alphabetical"
              },
              "icon": "lucide-folder-closed",
              "title": "Files"
            }
          },
          {
            "id": "92db9c16a9d82e93",
            "type": "leaf",
            "pane-relief:history-v1": {
              "pos": 0,
              "stack": [
                {
                  "state": "{}",
                  "eState": "{}"
                }
              ]
            },
            "state": {
              "type": "search",
              "state": {
                "query": "",
                "matchingCase": true,
                "explainSearch": false,
                "collapseAll": false,
                "extraContext": false,
                "sortOrder": "alphabetical"
              },
              "icon": "lucide-search",
              "title": "Search"
            }
          },
          {
            "id": "62d998da8c83e79a",
            "type": "leaf",
            "pane-relief:history-v1": {
              "pos": 0,
              "stack": [
                {
                  "state": "{}",
                  "eState": "{}"
                }
              ]
            },
            "state": {
              "type": "starred",
              "state": {},
              "icon": "lucide-file",
              "title": "Plugin no longer active"
            }
          }
        ]
      }
    ],
    "direction": "horizontal",
    "width": 200
  },
  "right": {
    "id": "2b3a55884ce239a9",
    "type": "split",
    "children": [
      {
        "id": "e4a73a6afb6e881a",
        "type": "tabs",
        "children": [
          {
            "id": "6bd8944ad57375a2",
            "type": "leaf",
            "pane-relief:history-v1": {
              "pos": 0,
              "stack": [
                {
                  "state": "{}",
                  "eState": "{}"
                }
              ]
            },
            "state": {
              "type": "backlink",
              "state": {
                "file": "Intrend Engineering/Kubernetes.md",
                "collapseAll": false,
                "extraContext": false,
                "sortOrder": "alphabetical",
                "showSearch": false,
                "searchQuery": "",
                "backlinkCollapsed": false,
                "unlinkedCollapsed": true
              },
              "icon": "links-coming-in",
              "title": "Backlinks for Kubernetes"
            }
          },
          {
            "id": "de251980df73cfeb",
            "type": "leaf",
            "pane-relief:history-v1": {
              "pos": 0,
              "stack": [
                {
                  "state": "{}",
                  "eState": "{}"
                }
              ]
            },
            "state": {
              "type": "outgoing-link",
              "state": {
                "file": "Intrend Engineering/Kubernetes.md",
                "linksCollapsed": false,
                "unlinkedCollapsed": true
              },
              "icon": "links-going-out",
              "title": "Outgoing links from Kubernetes"
            }
          },
          {
            "id": "22c7582bdb479a05",
            "type": "leaf",
            "pane-relief:history-v1": {
              "pos": 0,
              "stack": [
                {
                  "state": "{}",
                  "eState": "{}"
                }
              ]
            },
            "state": {
              "type": "advanced-tables-toolbar",
              "state": {},
              "icon": "lucide-file",
              "title": "Plugin no longer active"
            }
          },
          {
            "id": "708b8864c047f8aa",
            "type": "leaf",
            "pane-relief:history-v1": {
              "pos": 0,
              "stack": [
                {
                  "state": "{}",
                  "eState": "{}"
                }
              ]
            },
            "state": {
              "type": "all-properties",
              "state": {
                "sortOrder": "frequency",
                "showSearch": false,
                "searchQuery": ""
              },
              "icon": "lucide-archive",
              "title": "All properties"
            }
          },
          {
            "id": "0bddfe6b80d346fa",
            "type": "leaf",
            "pane-relief:history-v1": {
              "pos": 0,
              "stack": [
                {
                  "state": "{}",
                  "eState": "{}"
                }
              ]
            },
            "state": {
              "type": "outline",
              "state": {
                "file": "Intrend Engineering/Kubernetes.md"
              },
              "icon": "lucide-list",
              "title": "Outline of Kubernetes"
            }
          }
        ],
        "currentTab": 4
      }
    ],
    "direction": "horizontal",
    "width": 300,
    "collapsed": true
  },
  "left-ribbon": {
    "hiddenItems": {
      "templates:Insert template": false,
      "command-palette:Open command palette": false,
      "graph:Open graph view": false,
      "darlal-switcher-plus:Open in Headings Mode": false,
      "darlal-switcher-plus:Open Symbols for the active editor": false,
      "templater-obsidian:Templater": false,
      "float-search:Search Obsidian In Modal": false
    }
  },
  "active": "1e41539860bc5a7d",
  "ophidian:layout-settings": {
    "pane-relief:focus-lock": true
  },
  "lastOpenFiles": [
    "Intrend Engineering/Github Actions + Docker Automation.md",
    "Intrend Engineering/Design.md",
    "Intrend Engineering/Talos.md",
    "Intrend Engineering/Untitled.md",
    "Intrend Engineering/Postgres.md",
    "Intrend Engineering/Proxies.md",
    "Intrend Engineering/Proxmox.md",
    "Intrend Engineering/SSL.md",
    "Intrend Engineering/ArgoCD + Kustomize Helm.md",
    "Intrend Engineering/Apache Pulsar.md",
    "Intrend Engineering/Untitled",
    "Intrend Engineering/Kubernetes.md",
    "Intrend Engineering/Terraform.md",
    "Pasted image 20241010214051.png",
    "User relevance.md",
    "Untitled 1.md",
    "Intrend Engineering/Why Kafka.md",
    "Intrend Engineering/Intrend LOG.md",
    "Intrend Engineering/Handling DB Transactions.md",
    "Intrend Engineering/Error Tracking with Sentry.md",
    "Intrend Engineering/Emails.md",
    "Intrend Engineering/Redpanda.md",
    "Intrend Engineering/STAR Problems.md",
    "Intrend Research/Colors.md",
    "Intrend Engineering/Production Setup.md",
    "Intrend Engineering/Persistent Volumes.md",
    "attachments/Pasted image 20241010160352.png",
    "Intrend Engineering/Asyncio.md",
    "Intrend Engineering/Python.md",
    "attachments/Pasted image 20240921122319.png",
    "Intrend Research",
    "Intrend Engineering",
    "docs/SQL",
    "Code/Poetry",
    "attachments/Pasted image 20240723175205.png",
    "attachments/Pasted image 20240723175120.png",
    "Templates",
    "Code",
    "Personal",
    "ML/Deep Learning",
    "ML",
    "attachments/Pasted image 20240708143231.png",
    "attachments/Pasted image 20240604181855.png",
    "attachments/Pasted image 20240601175345.png",
    "attachments/Pasted image 20221202190703.png",
    "attachments/Pasted image 20221202190928.png"
  ]
}